aiocrypto/__init__.py
aiocrypto/app.py
aiocrypto/errors.py
aiocrypto/types.py
AioCrypto-1.0.71.dist-info/LICENSE
AioCrypto-1.0.71.dist-info/METADATA
AioCrypto-1.0.71.dist-info/WHEEL
AioCrypto-1.0.71.dist-info/top_level.txt
AioCrypto-1.0.71.dist-info/RECORD
