Metadata-Version: 2.1
Name: AioCrypto
Version: 1.0.71
Summary: Async Crypto API for humans
Home-page: https://github.com/ErVinTract/AioCrypto
Author: ErVinTract
Author-email: ErVinTract@gmail.com
License: Apache2
Classifier: Development Status :: 5 - Production/Stable
Classifier: Environment :: Console
Classifier: Framework :: AsyncIO
Classifier: Intended Audience :: Developers
Classifier: License :: OSI Approved :: Apache Software License
Classifier: Programming Language :: Python :: 3.8
Classifier: Programming Language :: Python :: 3.9
Classifier: Programming Language :: Python :: 3.10
Classifier: Programming Language :: Python :: 3.11
Requires-Python: >=3.8
License-File: LICENSE
Requires-Dist: aiohttp <3.9.0,>=3.8.0
